<?xml version="1.0" encoding="UTF-8"?>
<part version="5.0" xml:lang="en-US" xmlns="http://docbook.org/ns/docbook" xmlns:xl="http://www.w3.org/1999/xlink">
    <title>Introducing Lustre</title>
    <partintro>
  <para><anchor xml:id="dbdoclet.50438249_pgfId-369630" xreflabel=""/>Part I provides background information to help you understand the Lustre architecture and how the major components fit together. You will find information in this section about:</para>
  </partintro>

  <xi:include href="UnderstandingLustre.xml" xmlns:xi="http://www.w3.org/2001/XInclude" />
  <xi:include href="UnderstandingLustreNetworking.xml" xmlns:xi="http://www.w3.org/2001/XInclude" />
  <xi:include href="UnderstandingFailover.xml" xmlns:xi="http://www.w3.org/2001/XInclude" />


</part>
